examples/__init__.py
examples/data_helper.py
examples/gesture_classification.py
examples/modelnet_classification.py
examples/myocardium_segmentation.py
thumoon/__init__.py
thumoon/base.py
thumoon/utils.py
thumoon/version.py
thumoon/generation/__init__.py
thumoon/generation/clustering.py
thumoon/generation/fusion.py
thumoon/generation/grid.py
thumoon/generation/neighbors.py
thumoon/generation/sparse.py
thumoon/learning/__init__.py
thumoon/learning/classification/__init__.py
thumoon/learning/classification/diffusion.py
thumoon/learning/classification/inductive.py
thumoon/learning/classification/transductive.py
thumoon/learning/clustering/__init__.py
thumoon/learning/clustering/spectral_clustering.py
thumoon-0.0.3.dist-info/LICENSE
thumoon-0.0.3.dist-info/METADATA
thumoon-0.0.3.dist-info/WHEEL
thumoon-0.0.3.dist-info/top_level.txt
thumoon-0.0.3.dist-info/RECORD
