Metadata-Version: 2.1
Name: thumoon
Version: 0.0.3
Summary: A python toolbox for hypergraph learning
Home-page: https://github.com/iMoonLab/THU-Moon
Author: Haojie Lin
Author-email: linhj18@mails.tsinghua.edu.cn
License: UNKNOWN
Platform: UNKNOWN
Classifier: Programming Language :: Python :: 3
Classifier: License :: OSI Approved :: MIT License
Classifier: Operating System :: OS Independent
Requires-Dist: numpy
Requires-Dist: cvxpy (>=1.0)
Requires-Dist: matplotlib
Requires-Dist: scipy
Requires-Dist: scikit-learn
